zipfai/__init__.py
zipfai/_version.py
zipfai/exceptions.py
zipfai/utils.py
zipfai-0.0.1.dist-info/LICENSE
zipfai-0.0.1.dist-info/METADATA
zipfai-0.0.1.dist-info/WHEEL
zipfai-0.0.1.dist-info/top_level.txt
zipfai-0.0.1.dist-info/RECORD
